face_recognition_models/__init__.py
face_recognition_models/models/dlib_face_recognition_resnet_model_v1.dat
face_recognition_models/models/shape_predictor_68_face_landmarks.dat
face_recognition_models-0.1.3.dist-info/DESCRIPTION.rst
face_recognition_models-0.1.3.dist-info/METADATA
face_recognition_models-0.1.3.dist-info/RECORD
face_recognition_models-0.1.3.dist-info/WHEEL
face_recognition_models-0.1.3.dist-info/metadata.json
face_recognition_models-0.1.3.dist-info/top_level.txt
