Metadata-Version: 1.1
Name: face_recognition_models
Version: 0.1.3
Summary: Models used by the face_recognition package.
Home-page: https://github.com/ageitgey/face_recognition_models
Author: Adam Geitgey
Author-email: ageitgey@gmail.com
License: MIT license
Keywords: face_recognition
Platform: UNKNOWN
Classifier: Development Status :: 2 - Pre-Alpha
Classifier: Intended Audience :: Developers
Classifier: License :: OSI Approved :: MIT License
Classifier: Natural Language :: English
Classifier: Programming Language :: Python :: 2
Classifier: Programming Language :: Python :: 2.6
Classifier: Programming Language :: Python :: 2.7
Classifier: Programming Language :: Python :: 3
Classifier: Programming Language :: Python :: 3.3
Classifier: Programming Language :: Python :: 3.4
Classifier: Programming Language :: Python :: 3.5
Classifier: Programming Language :: Python :: 3.6
